{
  "title": "Como o Scully nos ajudou a atingir 99 pontos no Lighthouse para uma plataforma B2C",
  "domains": ["recruitment_pm", "user_research_design", "sales_marketing"],
  "authorImg": "https://assets.website-files.com/5c4c30d0c49ea6746fafc90c/5ca74cfb04fdce15ea9266e2_ava-Ruslan%20Ponuzhdayev.jpg",
  "language": "pt",
  "bgImg": "https://assets.website-files.com/5c4c30d0c49ea6746fafc90c/60d445d24897dc4086b2c80f_Blog-Scully.png",
  "author": "Ruslan Ponuzhdayev",
  "position": "JS Developer",
  "date": "Fri Jul 16 2021 10:45:55 GMT+0000 (Coordinated Universal Time)",
  "seoDescription": "Aceleramos o carregamento geral da página e aumentamos a pontuação do farol da plataforma para 99-100. Além disso, conectar o Google eCommerce Marketing nos ajudou a ver várias áreas de melhoria no site e em aplicativos móveis para agilizar a jornada do usuário. Aprenda com nossa experiência como você pode aumentar o desempenho do site e a visibilidade do seu projeto usando o Scully e o Google Analytics. Além disso, vou ajudá-lo a superar possíveis dificuldades com integrações, uma vez que já passamos por isso :)"
}